{"short_name":"Mamurov E","first_name":"Eldor ","last_name":"Mamurov ","patrynomic":"Tursunovich","faculty":"Mexanika - mashinasozlik","kafedra":"Mashinasozlik texnologiyasi va avtomatlashtirish","uid":"zdjUSxQTua","availab":[{"day":1,"pair":1,"scheduleType":0,"denominator":false,"fullTime":true,"numerator":false,"roomData":{"building":"2","roomNumber":"102","roomType":"lecture","roomCapCurr":"75","roomCapOld":"","file_name":"OiznGIcomuEcDY.json","availab":[],"name":"2-102"}},{"day":4,"pair":1,"fullTime":false,"numerator":false,"denominator":true,"roomData":{"availab":[]}},{"day":5,"pair":1,"fullTime":true,"numerator":false,"denominator":false,"roomData":{"availab":[]}},{"day":3,"pair":2,"fullTime":false,"numerator":false,"denominator":true,"roomData":{"availab":[]}},{"day":4,"pair":2,"fullTime":true,"numerator":false,"denominator":false,"roomData":{"availab":[]}},{"day":5,"pair":2,"fullTime":true,"numerator":false,"denominator":false,"roomData":{"availab":[]}},{"day":5,"pair":5,"fullTime":true,"numerator":false,"denominator":false,"roomData":{"availab":[]}},{"day":2,"pair":4,"fullTime":false,"numerator":false,"denominator":true,"roomData":{"availab":[]}},{"day":3,"pair":4,"fullTime":false,"numerator":false,"denominator":true,"roomData":{"availab":[]}},{"day":1,"pair":2,"fullTime":true,"numerator":false,"denominator":false,"roomData":{"availab":[]}},{"day":1,"pair":3,"fullTime":true,"numerator":false,"denominator":false,"roomData":{"availab":[]}},{"day":6,"pair":5,"fullTime":true,"numerator":false,"denominator":false,"roomData":{"availab":[]}}],"file_name":"zdjUSxQTua.json"}