{"name":"Mexatronika va robototexnika","course":3,"subjects":[{"subjectName":"Kasbiy Psixologiya","lecture":"15","practice":"15","lab":"0","teacher":{"37-20 MR":{"week":15,"lecture":{"name":"Usmonova M","uid":"EDwVzKNjCy"},"practice":{"name":"Usmonova M","uid":"EDwVzKNjCy"},"lab":{"name":"","uid":""}}}},{"subjectName":"Ekologiya","lecture":"15","practice":"15","lab":"15","teacher":{"37-20 MR":{"week":15,"lecture":{"name":"Qurbonova U","uid":"DivSZAGlFJ"},"practice":{"name":"Qurbonova U","uid":"DivSZAGlFJ"},"lab":{"name":"Qurbonova U","uid":"DivSZAGlFJ"}}}},{"subjectName":"Boshqarish nazariyasi","lecture":"30","practice":"15","lab":"0","teacher":{"37-20 MR":{"week":15,"lecture":{"name":"Sayitov S","uid":"zUTzYtdDvX"},"practice":{"name":"Raximov A","uid":"metDWbgpPg"},"lab":{"name":"","uid":""}}}},{"subjectName":"Mexatron modullar va ularni konstruktsiyalash","lecture":"30","practice":"15","lab":"15","teacher":{"37-20 MR":{"week":15,"lecture":{"name":"Xusanov Y","uid":"clJHSkYRzx"},"practice":{"name":"Xusanov Y","uid":"clJHSkYRzx"},"lab":{"name":"","uid":""}}}},{"subjectName":"Mikrokontrollerlar va ularni dasturlash asoslari","lecture":"30","practice":"15","lab":"15","teacher":{"37-20 MR":{"week":15,"lecture":{"name":"To\u2018xtasinov A","uid":"hwGTNRfYzv"},"practice":{"name":"Zokirov S","uid":"StMiiyFsTT"},"lab":{"name":"Zokirov S","uid":"StMiiyFsTT"}}}},{"subjectName":"Mashinasozlik t\u0435xnologiyasi asoslari","lecture":"45","practice":"45","lab":"0","teacher":{"37-20 MR":{"week":15,"lecture":{"name":"Mamurov E","uid":"zdjUSxQTua"},"practice":{"name":"Akramov M","uid":"wwzCcmUXAL"},"lab":{"name":"","uid":""}}}},{"subjectName":"Falsafa","lecture":"30","practice":"30","lab":"0"}],"file_name":"1668678005.json","numOfWeeks":15}