{"short_name":"Turg\u2018unov D","last_name":"Turg\u2018unov","first_name":"Dilmurod","patrynomic":"","faculty":"Yengil sanoat va to'qimachilik","kafedra":"Tabiiy tolalar","uid":"oRUWZsrtZb","file_name":"oRUWZsrtZb.json","availab":[{"day":3,"pair":1,"fullTime":true,"numerator":false,"denominator":false,"roomData":{"availab":[]}},{"day":1,"pair":1,"fullTime":false,"numerator":true,"denominator":false,"roomData":{"availab":[]}},{"day":2,"pair":1,"fullTime":false,"numerator":true,"denominator":false,"roomData":{"availab":[]}}]}