{"building":"4","roomNumber":"302","roomType":"practice","roomCapOld":24,"roomCapCurr":24,"file_name":"GrXuXaMBnhMigQ.json","availab":[{"day":2,"pair":1,"fullTime":false,"numerator":true,"denominator":false,"teacherData":{"availab":[]}},{"day":2,"pair":1,"fullTime":false,"numerator":false,"denominator":true,"teacherData":{"availab":[]}},{"day":1,"pair":2,"fullTime":true,"numerator":false,"denominator":false,"teacherData":{"availab":[]}},{"day":6,"pair":1,"fullTime":false,"numerator":true,"denominator":false,"teacherData":{"availab":[]}},{"day":6,"pair":1,"fullTime":false,"numerator":false,"denominator":true,"teacherData":{"availab":[]}},{"day":2,"pair":2,"fullTime":true,"numerator":false,"denominator":false,"teacherData":{"availab":[]}},{"day":5,"pair":1,"fullTime":true,"numerator":false,"denominator":false,"teacherData":{"availab":[]}},{"day":1,"pair":1,"fullTime":false,"numerator":true,"denominator":false,"teacherData":{"availab":[]}},{"day":1,"pair":1,"fullTime":false,"numerator":false,"denominator":true,"teacherData":{"availab":[]}},{"day":4,"pair":1,"fullTime":true,"numerator":false,"denominator":false,"teacherData":{"availab":[]}},{"day":3,"pair":1,"fullTime":true,"numerator":false,"denominator":false,"teacherData":{"availab":[]}},{"day":1,"pair":3,"fullTime":true,"numerator":false,"denominator":false,"teacherData":{"availab":[]}},{"day":4,"pair":2,"fullTime":true,"numerator":false,"denominator":false,"teacherData":{"availab":[]}},{"day":3,"pair":3,"fullTime":true,"numerator":false,"denominator":false,"teacherData":{"availab":[]}},{"day":6,"pair":2,"fullTime":true,"numerator":false,"denominator":false,"teacherData":{"availab":[]}},{"day":2,"pair":3,"fullTime":true,"numerator":false,"denominator":false,"teacherData":{"availab":[]}},{"day":4,"pair":3,"fullTime":true,"numerator":false,"denominator":false,"teacherData":{"availab":[]}},{"day":3,"pair":2,"fullTime":true,"numerator":false,"denominator":false,"teacherData":{"availab":[]}}]}