{"building":"1","roomNumber":"408","roomType":"practice","roomCapOld":24,"roomCapCurr":24,"file_name":"zxgnafSForYyDR.json","availab":[{"day":2,"pair":3,"fullTime":false,"numerator":true,"denominator":false,"teacherData":{"availab":[]}},{"day":2,"pair":3,"fullTime":false,"numerator":false,"denominator":true,"teacherData":{"availab":[]}},{"day":3,"pair":1,"fullTime":true,"numerator":false,"denominator":false,"teacherData":{"availab":[]}},{"day":4,"pair":2,"fullTime":false,"numerator":true,"denominator":false,"teacherData":{"availab":[]}},{"day":4,"pair":2,"fullTime":false,"numerator":false,"denominator":true,"teacherData":{"availab":[]}},{"day":5,"pair":2,"fullTime":false,"numerator":true,"denominator":false,"teacherData":{"availab":[]}},{"day":5,"pair":2,"fullTime":false,"numerator":false,"denominator":true,"teacherData":{"availab":[]}}]}