{"short_name":"Akramov  ","last_name":"Akramov ","first_name":" Axror ","patrynomic":"Adxamjon o\u2018g\u2018li","faculty":"Qurilish","kafedra":"Muhandislik kommunikatsiyalari qurilishi va montaji","uid":"ZfKCQamvAb","file_name":"ZfKCQamvAb.json","availab":[{"day":5,"pair":2,"fullTime":true,"numerator":false,"denominator":false,"roomData":{"availab":[]}},{"day":3,"pair":3,"fullTime":true,"numerator":false,"denominator":false,"roomData":{"availab":[]}},{"day":5,"pair":3,"fullTime":true,"numerator":false,"denominator":false,"roomData":{"availab":[]}},{"day":1,"pair":4,"fullTime":true,"numerator":false,"denominator":false,"roomData":{"availab":[]}},{"day":1,"pair":2,"fullTime":true,"numerator":false,"denominator":false,"roomData":{"availab":[]}}]}