{"building":"2","roomNumber":"204","roomType":"lecture","roomCapOld":52,"roomCapCurr":52,"availab":[{"day":1,"pair":1,"scheduleType":0,"denominator":false,"fullTime":true,"numerator":false,"teacherData":{"short_name":"Xusanov Y","first_name":"Yunusali","last_name":"Xusanov","patrynomic":"Yuldashaliyevich","faculty":"Mexanika - mashinasozlik","kafedra":"Oliy matematika","uid":"clJHSkYRzx","file_name":"clJHSkYRzx.json","name":"Xusanov Yunusali Yuldashaliyevich","availab":[]}},{"day":6,"pair":1,"scheduleType":0,"denominator":false,"fullTime":true,"numerator":false,"teacherData":{"short_name":"Gaziyev X","first_name":"Xaydarali ","last_name":"Gaziyev ","patrynomic":"Ortikovich","faculty":"Ishlab chiqarishda boshqaruv","kafedra":"Menejment","uid":"Kfegrnflbh","availab":[],"file_name":"Kfegrnflbh.json","name":"Gaziyev Xaydarali Ortikovich"}},{"day":6,"pair":2,"scheduleType":0,"denominator":false,"fullTime":true,"numerator":false,"teacherData":{"short_name":"Gaziyev X","first_name":"Xaydarali ","last_name":"Gaziyev ","patrynomic":"Ortikovich","faculty":"Ishlab chiqarishda boshqaruv","kafedra":"Menejment","uid":"Kfegrnflbh","availab":[],"file_name":"Kfegrnflbh.json","name":"Gaziyev Xaydarali Ortikovich"}},{"day":5,"pair":1,"scheduleType":0,"denominator":false,"fullTime":true,"numerator":false,"teacherData":{"short_name":"Qosimova Z","first_name":"Zamira ","last_name":"Qosimova ","patrynomic":"Medatovna","faculty":"Mexanika - mashinasozlik","kafedra":"Mashinasozlik texnologiyasi va avtomatlashtirish","uid":"LZWGDiYkGW","file_name":"LZWGDiYkGW.json","name":"Qosimova Zamira Medatovna","availab":[]}},{"day":1,"pair":3,"scheduleType":0,"denominator":false,"fullTime":true,"numerator":false,"teacherData":{"short_name":"Xodjaev S","first_name":"Sanjar ","last_name":"Xodjaev ","patrynomic":"Muxammedovich","faculty":"Mexanika - mashinasozlik","kafedra":"Yer usti transport tizimlari va ularni ekspluatatsiyasi","uid":"kKBdsplnJW","file_name":"kKBdsplnJW.json","name":"Xodjaev Sanjar Muxammedovich","availab":[]}},{"day":2,"pair":1,"fullTime":true,"numerator":false,"denominator":false,"teacherData":{"availab":[]}},{"day":2,"pair":4,"fullTime":true,"numerator":false,"denominator":false,"teacherData":{"availab":[]}},{"day":1,"pair":4,"fullTime":true,"numerator":false,"denominator":false,"teacherData":{"availab":[]}},{"day":3,"pair":4,"fullTime":true,"numerator":false,"denominator":false,"teacherData":{"availab":[]}},{"day":6,"pair":4,"fullTime":true,"numerator":false,"denominator":false,"teacherData":{"availab":[]}}],"file_name":"tCOvYEcJMgwsEK.json"}