{"building":"6","roomNumber":"308","roomType":"practice","roomCapOld":25,"roomCapCurr":25,"availab":[{"day":1,"pair":1,"scheduleType":0,"denominator":false,"fullTime":true,"numerator":false,"teacherData":{"short_name":"Maxmudov S","first_name":"Sodirjon ","last_name":"Maxmudov ","patrynomic":"Yusufalievich","faculty":"Kimyo texnologiya","kafedra":"Hayot faoliyati xavfsizligi","uid":"lEzTRQkDvW","file_name":"lEzTRQkDvW.json","name":"Maxmudov Sodirjon Yusufalievich","availab":[]}},{"day":1,"pair":2,"scheduleType":0,"denominator":false,"fullTime":true,"numerator":false,"teacherData":{"short_name":"Abdug\u2019aniev N","first_name":"Nazirjon ","last_name":"Abdug\u2019aniev ","patrynomic":"Nabijonovich","faculty":"Kimyo texnologiya","kafedra":"Hayot faoliyati xavfsizligi","uid":"nioJmaDAHh","file_name":"nioJmaDAHh.json","name":"Abdug\u2019aniev Nazirjon Nabijonovich","availab":[]}},{"day":3,"pair":1,"scheduleType":0,"denominator":false,"fullTime":true,"numerator":false,"teacherData":{"short_name":"Maxmudov S","first_name":"Sodirjon ","last_name":"Maxmudov ","patrynomic":"Yusufalievich","faculty":"Kimyo texnologiya","kafedra":"Hayot faoliyati xavfsizligi","uid":"lEzTRQkDvW","availab":[],"file_name":"lEzTRQkDvW.json","name":"Maxmudov Sodirjon Yusufalievich"}},{"day":3,"pair":2,"scheduleType":0,"denominator":false,"fullTime":true,"numerator":false,"teacherData":{"short_name":"Meliboyev I","first_name":"Ilxomjon","last_name":"Meliboyev ","patrynomic":"Abduraxmon o\u2019g\u2019li","faculty":"Kimyo texnologiya","kafedra":"Hayot faoliyati xavfsizligi","uid":"YTBLHmBVNP","file_name":"YTBLHmBVNP.json","name":"Meliboyev Ilxomjon Abduraxmon o\u2019g\u2019li","availab":[]}},{"day":5,"pair":1,"fullTime":false,"numerator":true,"denominator":false,"teacherData":{"availab":[]}},{"day":5,"pair":1,"fullTime":false,"numerator":false,"denominator":true,"teacherData":{"availab":[]}},{"day":4,"pair":1,"fullTime":true,"numerator":false,"denominator":false,"teacherData":{"availab":[]}},{"day":2,"pair":4,"fullTime":true,"numerator":false,"denominator":false,"teacherData":{"availab":[]}},{"day":3,"pair":4,"fullTime":true,"numerator":false,"denominator":false,"teacherData":{"availab":[]}},{"day":1,"pair":4,"fullTime":true,"numerator":false,"denominator":false,"teacherData":{"availab":[]}},{"day":5,"pair":4,"fullTime":true,"numerator":false,"denominator":false,"teacherData":{"availab":[]}},{"day":4,"pair":4,"fullTime":true,"numerator":false,"denominator":false,"teacherData":{"availab":[]}},{"day":2,"pair":2,"fullTime":true,"numerator":false,"denominator":false,"teacherData":{"availab":[]}},{"day":2,"pair":1,"fullTime":true,"numerator":false,"denominator":false,"teacherData":{"availab":[]}},{"day":4,"pair":2,"fullTime":true,"numerator":false,"denominator":false,"teacherData":{"availab":[]}}],"file_name":"XLxAMyhJaXFSDP.json"}